cid/__init__.py
cid/_version.py
cid/base.py
cid/cli.py
cid/common.py
cid/exceptions.py
cid/export.py
cid/logger.py
cid/plugin.py
cid/utils.py
cid/builtin/__init__.py
cid/builtin/core/__init__.py
cid/builtin/core/data/resources.yaml
cid/builtin/core/data/datasets/cid/compute.json
cid/builtin/core/data/datasets/cid/ec2_running_cost.json
cid/builtin/core/data/datasets/cid/s3_view.json
cid/builtin/core/data/datasets/cid/summary_view.json
cid/builtin/core/data/datasets/co/dataset.json
cid/builtin/core/data/datasets/cudos/hourly_view.json
cid/builtin/core/data/datasets/cudos/resource_view.json
cid/builtin/core/data/datasets/kpi/kpi_ebs_snap.json
cid/builtin/core/data/datasets/kpi/kpi_ebs_storage_all.json
cid/builtin/core/data/datasets/kpi/kpi_instance_all.json
cid/builtin/core/data/datasets/kpi/kpi_s3_storage_all.json
cid/builtin/core/data/datasets/kpi/kpi_tracker.json
cid/builtin/core/data/datasets/shared/customer_all.json
cid/builtin/core/data/datasets/trends/daily_anomaly_detection.json
cid/builtin/core/data/datasets/trends/monthly_anomaly_detection.json
cid/builtin/core/data/datasets/trends/monthly_bill_by_account.json
cid/builtin/core/data/permissions/dashboard_permissions.json
cid/builtin/core/data/permissions/dashboard_permissions_namespace.json
cid/builtin/core/data/permissions/data_set_permissions.json
cid/builtin/core/data/permissions/data_set_rls_permissions.json
cid/builtin/core/data/permissions/data_source_permissions.json
cid/builtin/core/data/permissions/folder_permissions.json
cid/builtin/core/data/queries/cid/compute_savings_plan_eligible_spend.sql
cid/builtin/core/data/queries/cid/ec2_running_cost.sql
cid/builtin/core/data/queries/cid/ri_sp_mapping.sql
cid/builtin/core/data/queries/cid/s3.sql
cid/builtin/core/data/queries/cid/summary_view.sql
cid/builtin/core/data/queries/co/all_options.sql
cid/builtin/core/data/queries/co/auto_scale.json
cid/builtin/core/data/queries/co/auto_scale_options.sql
cid/builtin/core/data/queries/co/ebs_volume.json
cid_cmd-4.4.6.dist-info/licenses/LICENSE
cid_cmd-4.4.6.dist-info/METADATA
cid_cmd-4.4.6.dist-info/WHEEL
cid_cmd-4.4.6.dist-info/entry_points.txt
cid_cmd-4.4.6.dist-info/top_level.txt
cid_cmd-4.4.6.dist-info/RECORD
