Metadata-Version: 2.4
Name: cid-cmd
Version: 4.4.6
Summary: Cloud Intelligence Dashboards deployment helper tool
Home-page: https://github.com/aws-samples/aws-cudos-framework-deployment
Author: AWS CUDOS Team
License: MIT
Keywords: aws,cmd,cli,cost intelligence dashboards
Classifier: Development Status :: 4 - Beta
Classifier: License :: OSI Approved :: MIT License
Classifier: Programming Language :: Python :: 3
Classifier: Programming Language :: Python :: 3.10
Classifier: Programming Language :: Python :: 3.11
Classifier: Programming Language :: Python :: 3.12
Classifier: Programming Language :: Python :: 3.13
License-File: LICENSE
Requires-Dist: setuptools
Requires-Dist: boto3>=1.35.86
Requires-Dist: Click>=8.0
Requires-Dist: PyYAML
Requires-Dist: requests
Requires-Dist: tzlocal>=4.0
Requires-Dist: six>=1.15
Requires-Dist: InquirerPy
Requires-Dist: tqdm
Requires-Dist: filelock>=3.20.3
Dynamic: license-file
